interpret/Buffer.py
interpret/Lexer.py
interpret/Parser.py
interpret/Token.py
interpret/Visitor.py
interpret/__init__.py
interpret/cli.py
interpret/file_interface.py
interpret/helpers.py
interpret/interpreter.py
interpret/tm_helpers.py
interpret/utils.py
automython-1.2.0.dist-info/LICENSE.txt
automython-1.2.0.dist-info/METADATA
automython-1.2.0.dist-info/WHEEL
automython-1.2.0.dist-info/entry_points.txt
automython-1.2.0.dist-info/top_level.txt
automython-1.2.0.dist-info/RECORD
