Metadata-Version: 2.1
Name: automython
Version: 1.2.0
Summary: A simplistic programming language interpreter to Python to help students grasp finite automata theory programmatically and with a computed graph through visualization libraries.
Home-page: https://github.com/mkantrr/automython
Author: Matthew Kanter
Author-email: Matthew Kanter <matt@matutu.dev>
Maintainer-email: Matthew Kanter <matt@matutu.dev>
License: The MIT License (MIT)
Keywords: automata,finite,compiler,interpreter,theory,computational theory,non-deterministic,turing,machine,state
Classifier: License :: OSI Approved :: MIT License
Classifier: Programming Language :: Python :: 3
Classifier: Operating System :: OS Independent
Requires-Python: >=3.8
License-File: LICENSE.txt
Requires-Dist: automata-lib[visual] >=8.2.0
Requires-Dist: pandas >=2.2.0
Requires-Dist: ipython >=8.22.2
Requires-Dist: forbiddenfruit >=0.1.4
